libro_ai/__init__.py
libro_ai/_version.py
libro_ai/extensions.py
libro_ai/chat/__init__.py
libro_ai/chat/chat_message.py
libro_ai/chat/chat_record.py
libro_ai/chat/debug_executor.py
libro_ai/chat/debug_provider.py
libro_ai/chat/executor.py
libro_ai/chat/item.py
libro_ai/chat/langchain_variable.py
libro_ai/chat/langchain_variable_executor.py
libro_ai/chat/object.py
libro_ai/chat/object_manager.py
libro_ai/chat/openai_chat_executor.py
libro_ai/chat/openai_chat_provider.py
libro_ai/chat/provider.py
libro_ai/chat/qwen_chat_executor.py
libro_ai/chat/qwen_chat_provider.py
libro_ai/chat/source.py
libro_ai/chat/utils.py
libro_ai/magics/__init__.py
libro_ai/magics/exception.py
libro_ai/magics/prompt_magic.py
libro_ai/utils/__init__.py
libro_ai/utils/base.py
libro_ai/utils/inspector.py
libro_ai/utils/langchain.py
libro_ai-0.1.13.dist-info/METADATA
libro_ai-0.1.13.dist-info/WHEEL
libro_ai-0.1.13.dist-info/RECORD
